datadez/__init__.py
datadez/columns.py
datadez/filter.py
datadez/multilabel.py
datadez/summarize.py
datadez/summary.py
datadez/transform.py
datadez/vectorize.py
datadez/dataviz/__init__.py
datadez/dataviz/chord_diagram.py
datadez/dataviz/color.py
datadez/dataviz/multilabel_plot.py
datadez-0.1.dev3.dist-info/DESCRIPTION.rst
datadez-0.1.dev3.dist-info/METADATA
datadez-0.1.dev3.dist-info/RECORD
datadez-0.1.dev3.dist-info/WHEEL
datadez-0.1.dev3.dist-info/metadata.json
datadez-0.1.dev3.dist-info/top_level.txt
