Metadata-Version: 2.0
Name: datadez
Version: 0.1.dev3
Summary: Inspect, filter and balance your dataset
Home-page: https://github.com/dezounet/datadez
Author: dezounet
Author-email: dezonthenet@gmail.com
License: MIT
Download-URL: https://github.com/dezounet/datadez/archive/0.1.tar.gz
Keywords: dataset,inspect,filter,balance
Platform: UNKNOWN
Requires-Dist: numpy (>=1.13.3)
Requires-Dist: pandas (>=0.21.0)
Requires-Dist: future
Requires-Dist: nltk
Requires-Dist: sklearn
Requires-Dist: scipy
